{
  "recentFiles": [
    {
      "basename": "14 屏幕颜色制作玻璃效果",
      "path": "引擎Unity3D/3 URP精粹/雪风/14 屏幕颜色制作玻璃效果.md"
    },
    {
      "basename": "URP _ 热扭曲效果 - 哔哩哔哩",
      "path": "zBuffer/URP _ 热扭曲效果 - 哔哩哔哩.md"
    },
    {
      "basename": "02 UV操作",
      "path": "技术美术/1 渲染雅集/02 UV操作.md"
    },
    {
      "basename": "1 ShaderLab",
      "path": "引擎Unity3D/3 URP精粹/1 ShaderLab.md"
    },
    {
      "basename": "URP 渲染优化总结",
      "path": "zBuffer/URP 渲染优化总结.md"
    },
    {
      "basename": "【笔记】URP 透明物体截屏 - 哔哩哔哩",
      "path": "zBuffer/【笔记】URP 透明物体截屏 - 哔哩哔哩.md"
    },
    {
      "basename": "2 URP",
      "path": "引擎Unity3D/3 URP精粹/2 URP.md"
    },
    {
      "basename": "4 后处理",
      "path": "引擎Unity3D/3 URP精粹/后处理/4 后处理.md"
    },
    {
      "basename": "01 Trick！",
      "path": "技术美术/1 渲染雅集/01 Trick！.md"
    },
    {
      "basename": "《CS Primer》",
      "path": "引擎Unity3D/1 Unity精粹/《CS Primer》.md"
    },
    {
      "basename": "3_72 command buffer 及 urp 概述",
      "path": "zBuffer/3_72 command buffer 及 urp 概述.md"
    },
    {
      "basename": "18 性能拔尖的模糊 - 双重 Kasase 模糊",
      "path": "引擎Unity3D/3 URP精粹/雪风/18 性能拔尖的模糊 - 双重 Kasase 模糊.md"
    },
    {
      "basename": "17 Kawase 高性能模糊",
      "path": "引擎Unity3D/3 URP精粹/雪风/17 Kawase 高性能模糊.md"
    },
    {
      "basename": "光照探针，反射探针，光照烘焙",
      "path": "zBuffer/光照探针，反射探针，光照烘焙.md"
    },
    {
      "basename": "5 CommandBuffer",
      "path": "引擎Unity3D/3 URP精粹/5 CommandBuffer.md"
    },
    {
      "basename": "《Unity Primer》",
      "path": "引擎Unity3D/1 Unity精粹/《Unity Primer》.md"
    },
    {
      "basename": "《Unity设计模式》",
      "path": "引擎Unity3D/1 Unity精粹/《Unity设计模式》.md"
    },
    {
      "basename": "07 空间",
      "path": "技术美术/1 渲染雅集/07 空间.md"
    },
    {
      "basename": "3 Render Feature",
      "path": "引擎Unity3D/3 URP精粹/3 Render Feature.md"
    },
    {
      "basename": "36 造一个 PBR 的轮子",
      "path": "引擎Unity3D/3 URP精粹/雪风/36 造一个 PBR 的轮子.md"
    },
    {
      "basename": "34 SSPR屏幕空间平面反射",
      "path": "引擎Unity3D/3 URP精粹/雪风/34 SSPR屏幕空间平面反射.md"
    },
    {
      "basename": "33 光线步进 RayMarch 第一节入门",
      "path": "引擎Unity3D/3 URP精粹/雪风/33 光线步进 RayMarch 第一节入门.md"
    },
    {
      "basename": "26  制作 VEG 粒子特效",
      "path": "引擎Unity3D/3 URP精粹/雪风/26  制作 VEG 粒子特效.md"
    },
    {
      "basename": "27 ComputeShader 入门 实现 RendererFeature 后处理",
      "path": "引擎Unity3D/3 URP精粹/雪风/27 ComputeShader 入门 实现 RendererFeature 后处理.md"
    },
    {
      "basename": "24 Render Feature 制作特定模型外描边",
      "path": "引擎Unity3D/3 URP精粹/雪风/24 Render Feature 制作特定模型外描边.md"
    },
    {
      "basename": "15 屏幕深度制作护盾特效",
      "path": "引擎Unity3D/3 URP精粹/雪风/15 屏幕深度制作护盾特效.md"
    },
    {
      "basename": "20 景深和散景模糊——数学篇",
      "path": "引擎Unity3D/3 URP精粹/雪风/20 景深和散景模糊——数学篇.md"
    },
    {
      "basename": "19 径向模糊",
      "path": "引擎Unity3D/3 URP精粹/雪风/19 径向模糊.md"
    },
    {
      "basename": "TA 之路",
      "path": "引擎Unity3D/收藏夹/TA 之路.md"
    },
    {
      "basename": "04 景深",
      "path": "技术美术/3 后处理/04 景深.md"
    },
    {
      "basename": "ta101后处理",
      "path": "技术美术/3 后处理/ta101后处理.md"
    },
    {
      "basename": "02 Bloom",
      "path": "技术美术/3 后处理/02 Bloom.md"
    },
    {
      "basename": "工具流",
      "path": "Tools/工具流.md"
    },
    {
      "basename": "mermaid流图",
      "path": "zip/templates/mermaid流图.md"
    },
    {
      "basename": "markmap脑图",
      "path": "zip/templates/markmap脑图.md"
    },
    {
      "basename": "callout分栏",
      "path": "zip/templates/callout分栏.md"
    },
    {
      "basename": "中行卓隽卡交房租教程文字版 - 哔哩哔哩",
      "path": "zip/留学/中行卓隽卡交房租教程文字版 - 哔哩哔哩.md"
    },
    {
      "basename": "行李",
      "path": "zip/留学/行李.md"
    },
    {
      "basename": "缴费",
      "path": "zip/留学/缴费.md"
    },
    {
      "basename": "前往斯旺西",
      "path": "zip/留学/前往斯旺西.md"
    },
    {
      "basename": "死亡搁浅扫描特效",
      "path": "引擎Unity3D/收藏夹/死亡搁浅扫描特效.md"
    },
    {
      "basename": "实时渲染高级特性开发",
      "path": "引擎Unity3D/收藏夹/实时渲染高级特性开发.md"
    },
    {
      "basename": "Unity 几何着色器详解",
      "path": "引擎Unity3D/收藏夹/Unity 几何着色器详解.md"
    },
    {
      "basename": "Unity3D Shader： 科幻风线框渲染",
      "path": "引擎Unity3D/收藏夹/Unity3D Shader： 科幻风线框渲染.md"
    },
    {
      "basename": "Unity URP ColorGradingLut 分析与实现",
      "path": "引擎Unity3D/收藏夹/Unity URP ColorGradingLut 分析与实现.md"
    },
    {
      "basename": "01 自定义渲染管线",
      "path": "引擎Unity3D/4 Catlike Coding/《SRP》/01 自定义渲染管线.md"
    },
    {
      "basename": "02 Draw Call",
      "path": "引擎Unity3D/4 Catlike Coding/《SRP》/02 Draw Call.md"
    },
    {
      "basename": "辐射度量学",
      "path": "技术美术/7 PBR/辐射度量学.md"
    },
    {
      "basename": "从零开始的基于物理的渲染 (PBR)(2)：物理材质和物理相机",
      "path": "技术美术/7 PBR/从0开始PBR/从零开始的基于物理的渲染 (PBR)(2)：物理材质和物理相机.md"
    },
    {
      "basename": "从零开始的基于物理的渲染 (PBR)(4)：菲涅尔反射、微表面理论和宏观 BRDF",
      "path": "技术美术/7 PBR/从0开始PBR/从零开始的基于物理的渲染 (PBR)(4)：菲涅尔反射、微表面理论和宏观 BRDF.md"
    }
  ],
  "omittedPaths": [],
  "maxLength": null,
  "openType": "tab"
}