{
  "main": {
    "id": "0b7e167bde9c02bc",
    "type": "split",
    "children": [
      {
        "id": "b94cecc6fdea6d43",
        "type": "tabs",
        "children": [
          {
            "id": "4c7bca08cd3c2e63",
            "type": "leaf",
            "state": {
              "type": "canvas",
              "state": {
                "file": "图形学/DX12/龙书/DX12初始化.canvas",
                "viewState": {
                  "x": -468,
                  "y": 305,
                  "zoom": -0.8403433340115148
                }
              }
            }
          },
          {
            "id": "859daf37132094c6",
            "type": "leaf",
            "state": {
              "type": "markdown",
              "state": {
                "file": "图形学/DX12/龙书/DX12理论.md",
                "mode": "source",
                "source": false
              }
            }
          },
          {
            "id": "9ef88c15d4f0b027",
            "type": "leaf",
            "state": {
              "type": "markdown",
              "state": {
                "file": "技术美术/冯乐乐入门精要/Shader入门精要.md",
                "mode": "source",
                "source": false
              }
            }
          },
          {
            "id": "abfadc8e906a91c1",
            "type": "leaf",
            "state": {
              "type": "markdown",
              "state": {
                "file": "编程/C++/《C++ Primer 5th》.md",
                "mode": "source",
                "source": false
              }
            }
          }
        ],
        "currentTab": 1
      }
    ],
    "direction": "vertical"
  },
  "left": {
    "id": "a67566f3d324d3f8",
    "type": "split",
    "children": [
      {
        "id": "253c969ce5fb6548",
        "type": "tabs",
        "dimension": 62.589928057553955,
        "children": [
          {
            "id": "86b0a46618d8ba0a",
            "type": "leaf",
            "state": {
              "type": "quiet-outline",
              "state": {}
            }
          },
          {
            "id": "644549f2ea441a29",
            "type": "leaf",
            "state": {
              "type": "search",
              "state": {
                "query": "",
                "matchingCase": false,
                "explainSearch": false,
                "collapseAll": false,
                "extraContext": false,
                "sortOrder": "alphabetical"
              }
            }
          },
          {
            "id": "21a03d7ff7e78358",
            "type": "leaf",
            "state": {
              "type": "outline",
              "state": {
                "file": "图形学/DX12/龙书/DX12理论.md"
              }
            }
          }
        ]
      },
      {
        "id": "b49fb9eff2f6ac76",
        "type": "tabs",
        "dimension": 37.410071942446045,
        "children": [
          {
            "id": "6ea84489302e84b4",
            "type": "leaf",
            "state": {
              "type": "file-explorer",
              "state": {
                "sortOrder": "alphabetical"
              }
            }
          },
          {
            "id": "5461356f6f632385",
            "type": "leaf",
            "state": {
              "type": "starred",
              "state": {}
            }
          },
          {
            "id": "b718d4b7b66dbfbd",
            "type": "leaf",
            "state": {
              "type": "backlink",
              "state": {
                "file": "图形学/DX12/龙书/DX12理论.md",
                "collapseAll": false,
                "extraContext": false,
                "sortOrder": "alphabetical",
                "showSearch": false,
                "searchQuery": "",
                "backlinkCollapsed": true,
                "unlinkedCollapsed": true
              }
            }
          },
          {
            "id": "9d395a5bb522340c",
            "type": "leaf",
            "state": {
              "type": "outgoing-link",
              "state": {
                "file": "图形学/DX12/龙书/DX12理论.md",
                "linksCollapsed": true,
                "unlinkedCollapsed": true
              }
            }
          }
        ],
        "currentTab": 1
      }
    ],
    "direction": "horizontal",
    "width": 200
  },
  "right": {
    "id": "bd3717a50a592ecf",
    "type": "split",
    "children": [],
    "direction": "horizontal",
    "width": 200,
    "collapsed": true
  },
  "left-ribbon": {
    "hiddenItems": {
      "canvas:新建白板": false,
      "command-palette:打开命令面板": true,
      "oz-clear-unused-images:Clear Unused Images": false,
      "remotely-save:Remotely Save": false,
      "obsidian-focus-mode:Toggle Focus Mode (Shift + Click to show active pane only)": false,
      "templates:插入模板": false
    }
  },
  "active": "859daf37132094c6",
  "lastOpenFiles": [
    "Tools/工具流.md",
    "图形学/DX12/DirectXMath.md",
    "Tools/Obsidian/插件流.md",
    "Tools/Obsidian/Mermaid流图.md",
    "编程/C++/《C++ Primer 5th》.md",
    "编程/C++/《Effective C++ 3th》.md",
    "AI/Python/Python基础.md",
    "AI/Python/Numpy+Matplotlib.md",
    "虚幻引擎/1 指南/(31 条消息) 虚幻引擎 问题汇总_Codelk 的博客 - CSDN 博客/(31 条消息) 虚幻引擎 问题汇总_Codelk 的博客 - CSDN 博客.md",
    "编程/设计模式/工厂模式.md",
    "编程/C++/C++补充.md",
    "技术美术/冯乐乐入门精要/Shader入门精要.md",
    "图形学/DX12/BUG记录.md",
    "图形学/DX12/龙书/DX12理论.md",
    "图形学/DX12/龙书/脑图.md",
    "图形学/DX12/龙书/DX12初始化.canvas",
    "图形学/DX12/自研引擎/1 引擎开发环境部署.md",
    "图形学/DX12/自研引擎/2 DX12初始化.md",
    "AI/深度学习/快速入门.md",
    "AI/深度学习/《鱼书》.md",
    "README.md",
    "编程/C++/C++原理.md",
    "虚幻引擎/2 蓝图 & U++/101 蓝图.md",
    "Math/3D数学/3D数学.md",
    "Math/微积分/微积分基础.md",
    "Math/线性代数/线性代数基础.md",
    "Math/线性代数/矩阵论.md",
    "zip/images/image-20220702145045963.png",
    "虚幻引擎/6 动画",
    "zip/images/1682613248787.png",
    "zip/images/1682613248749.png",
    "zip/images/1682613248708.png",
    "zip/images/1682613248675.png",
    "zip/images/1682613248636.png",
    "zip/images/1682613248602.png",
    "zip/images/1682613248567.png",
    "zip/images/1682613248523.png",
    "zip/images/1682613248484.png",
    "zBuffer/最近种草了 AR 眼镜，想买来旅游露营追剧，推荐吗？爆火的 Nreal Air 是不是智商税？真实体验如何？/assets",
    "zBuffer/最近种草了 AR 眼镜，想买来旅游露营追剧，推荐吗？爆火的 Nreal Air 是不是智商税？真实体验如何？",
    "Zbuffer/DirectXMath 库标量函数 - Win32 apps",
    "Zbuffer/对游戏开发中的四元数的一些理解/assets",
    "Zbuffer/对游戏开发中的四元数的一些理解",
    "zip/images/TEST - Unreal Editor 2022-12-22 12-32-46.mp4",
    "Zbuffer/(19 条消息) 【Unity 编程】欧拉角与万向节死锁（图文版）_AndrewFan 的博客 - CSDN 博客/assets",
    "Zbuffer/(19 条消息) 【Unity 编程】欧拉角与万向节死锁（图文版）_AndrewFan 的博客 - CSDN 博客",
    "zip/images/Diagram 1.svg.xml",
    "Tools/Excalidraw/未命名.canvas",
    "未命名.canvas",
    "Software/未命名.canvas",
    "Tools/系统安全/未命名.canvas",
    "虚幻UE/4 特效/月神3/未命名.canvas",
    "啊.canvas"
  ]
}