{
  "main": {
    "id": "0b7e167bde9c02bc",
    "type": "split",
    "children": [
      {
        "id": "af01975e70e73712",
        "type": "tabs",
        "children": [
          {
            "id": "8d715da3c644dc96",
            "type": "leaf",
            "state": {
              "type": "markdown",
              "state": {
                "file": "引擎Unity3D/1 Unity精粹/《Unity Primer》.md",
                "mode": "source",
                "backlinks": false,
                "source": false
              }
            }
          },
          {
            "id": "611ad4af16a426fd",
            "type": "leaf",
            "state": {
              "type": "markdown",
              "state": {
                "file": "zBuffer/Unity Shader - 阴影方案总结.md",
                "mode": "source",
                "backlinks": false,
                "source": false
              }
            }
          },
          {
            "id": "95511858234987c3",
            "type": "leaf",
            "state": {
              "type": "markdown",
              "state": {
                "file": "图形学/1 图形系统/09 阴影.md",
                "mode": "source",
                "backlinks": false,
                "source": false
              }
            }
          },
          {
            "id": "6391a1ce9b10f577",
            "type": "leaf",
            "state": {
              "type": "markdown",
              "state": {
                "file": "zip/AI/深度学习/《鱼书》.md",
                "mode": "source",
                "backlinks": false,
                "source": false
              }
            }
          },
          {
            "id": "9ea9936255f05a8c",
            "type": "leaf",
            "state": {
              "type": "markdown",
              "state": {
                "file": "图形学/3 软渲染器/软光栅/透视矫正插值.md",
                "mode": "source",
                "backlinks": false,
                "source": false
              }
            }
          },
          {
            "id": "3dddcb5145d847c8",
            "type": "leaf",
            "state": {
              "type": "markdown",
              "state": {
                "file": "图形学/1 图形系统/06 深度测试.md",
                "mode": "source",
                "backlinks": false,
                "source": false
              }
            }
          },
          {
            "id": "96b9c68e1447b1cb",
            "type": "leaf",
            "state": {
              "type": "markdown",
              "state": {
                "file": "引擎Unity3D/3 URP精粹/1 ShaderLab.md",
                "mode": "source",
                "backlinks": false,
                "source": false
              }
            }
          },
          {
            "id": "8d09a7b82802f0f8",
            "type": "leaf",
            "state": {
              "type": "markdown",
              "state": {
                "file": "引擎Unity3D/2 Shader精粹/雪风/22 科幻扫描效果前篇.md",
                "mode": "source",
                "backlinks": false,
                "source": false
              }
            }
          },
          {
            "id": "3d9417467b62070a",
            "type": "leaf",
            "state": {
              "type": "markdown",
              "state": {
                "file": "图形学/0 3D数学/公式推导/02 视图变换.md",
                "mode": "source",
                "backlinks": false,
                "source": false
              }
            }
          },
          {
            "id": "279196c501d26be7",
            "type": "leaf",
            "state": {
              "type": "markdown",
              "state": {
                "file": "图形学/2 图形API/DX12/DirectXMath.md",
                "mode": "source",
                "backlinks": false,
                "source": false
              }
            }
          }
        ],
        "currentTab": 3
      }
    ],
    "direction": "vertical"
  },
  "left": {
    "id": "a67566f3d324d3f8",
    "type": "split",
    "children": [
      {
        "id": "253c969ce5fb6548",
        "type": "tabs",
        "dimension": 38.39928057553957,
        "children": [
          {
            "id": "86b0a46618d8ba0a",
            "type": "leaf",
            "state": {
              "type": "quiet-outline",
              "state": {}
            }
          },
          {
            "id": "644549f2ea441a29",
            "type": "leaf",
            "state": {
              "type": "search",
              "state": {
                "query": "",
                "matchingCase": false,
                "explainSearch": false,
                "collapseAll": false,
                "extraContext": false,
                "sortOrder": "alphabetical"
              }
            }
          },
          {
            "id": "21a03d7ff7e78358",
            "type": "leaf",
            "state": {
              "type": "outline",
              "state": {
                "file": "zip/AI/深度学习/《鱼书》.md"
              }
            }
          }
        ]
      },
      {
        "id": "c860fd12f8384878",
        "type": "tabs",
        "dimension": 20.14388489208633,
        "children": [
          {
            "id": "ffd75fe37a90e6ea",
            "type": "leaf",
            "state": {
              "type": "recent-files",
              "state": {}
            }
          }
        ]
      },
      {
        "id": "b49fb9eff2f6ac76",
        "type": "tabs",
        "dimension": 41.456834532374096,
        "children": [
          {
            "id": "6ea84489302e84b4",
            "type": "leaf",
            "state": {
              "type": "file-explorer",
              "state": {
                "sortOrder": "alphabetical"
              }
            }
          },
          {
            "id": "e71deaf0fc9fcfb8",
            "type": "leaf",
            "state": {
              "type": "bookmarks",
              "state": {}
            }
          },
          {
            "id": "359f689aa579d2fb",
            "type": "leaf",
            "state": {
              "type": "backlink",
              "state": {
                "file": "zip/AI/深度学习/《鱼书》.md",
                "collapseAll": true,
                "extraContext": false,
                "sortOrder": "alphabetical",
                "showSearch": false,
                "searchQuery": "",
                "backlinkCollapsed": false,
                "unlinkedCollapsed": true
              }
            }
          },
          {
            "id": "ba61e1d5651c49d1",
            "type": "leaf",
            "state": {
              "type": "outgoing-link",
              "state": {
                "file": "zip/AI/深度学习/《鱼书》.md",
                "linksCollapsed": true,
                "unlinkedCollapsed": true
              }
            }
          }
        ]
      }
    ],
    "direction": "horizontal",
    "width": 200
  },
  "right": {
    "id": "bd3717a50a592ecf",
    "type": "split",
    "children": [],
    "direction": "horizontal",
    "width": 200,
    "collapsed": true
  },
  "left-ribbon": {
    "hiddenItems": {
      "omnisearch:Omnisearch": true,
      "canvas:新建白板": false,
      "templates:插入模板": false,
      "command-palette:打开命令面板": true,
      "oz-clear-unused-images:Clear Unused Images": false,
      "remotely-save:Remotely Save": false,
      "obsidian-local-images-plus:Local Images Plus  0.15.7\r\nDownload media files": false,
      "markdown-table-editor:Open Markdown Table Editor": false,
      "obsidian-focus-mode:Toggle Focus Mode (Shift + Click to show active pane only)": false
    }
  },
  "active": "6391a1ce9b10f577",
  "lastOpenFiles": [
    "技术美术/1 渲染雅集/07 描边.md",
    "zBuffer/在 shader 中实现五种描边方法.md",
    "zip/images/43304e962aac52ea1de18183d092c485_MD5.jpg",
    "zip/images/173a69a697743ca9581cb0ba15aa24f9_MD5.png",
    "zip/images/5babaf79a82fcafdfc07dfa7529f2dcd_MD5.png",
    "zip/images/789ac058cafd8e14085ab6653ea3336d_MD5.png",
    "zip/images/3e6e46bd285c9a1d7ea8fceaf52133e3_MD5.png",
    "zip/images/dae617ea28bf736d24c53f850d391047_MD5.png",
    "zip/images/cd1e7434a594c30fdbe3fbcd1dd79fa6_MD5.jpg",
    "zip/images/da52410af27e90ce474b47aecd9ccf06_MD5.png",
    "zip/images/a61b10015edf8fe9a404e61593c279a5_MD5.png",
    "zip/images/69e5ca4b45d2b6583d5424057fbc56e2_MD5.png",
    "zBuffer/Unity Shader - 深度图基础及应用 - 简书.md",
    "zBuffer/Unity Shader - 消融效果原理与变体 - 简书.md",
    "zBuffer/Unity Shader - 阴影方案总结.md",
    "zBuffer/Unity Shader - 溶解方案总结.md",
    "zBuffer/Unity Shader - 描边方案总结.md",
    "技术美术/1 渲染雅集/06 溶解.md",
    "图形学/5 书籍/《RTR4》/7 阴影.md",
    "图形学/1 图形系统/09 阴影.md",
    "图形学/5 书籍/《RTR4》/15 非真实感渲染.md",
    "图形学/5 书籍/《RTR4》/5 着色基础.md",
    "图形学/5 书籍/《RTR4》/6 纹理化.md",
    "图形学/5 书籍/《RTR4》/资源.md",
    "引擎Unity3D/3 URP精粹/4 后处理.md",
    "引擎Unity3D/1 Unity精粹/《Unity Primer》.md",
    "引擎Unity3D/2 Shader精粹/雪风/17 Kawase 高性能模糊.md",
    "引擎Unity3D/2 Shader精粹/雪风/21 和散景模糊——实践篇.md",
    "引擎Unity3D/2 Shader精粹/雪风/20 景深和散景模糊——数学篇.md",
    "引擎Unity3D/2 Shader精粹/雪风/19 径向模糊.md",
    "技术美术/7 PBR/基于物理的渲染算法研究【U3D】.md",
    "技术美术/7 PBR/PBR总结.md",
    "技术美术/7 PBR/ta101PBR.md",
    "技术美术/7 PBR/辐射度量学.md",
    "技术美术/7 PBR/PBR疑问.md",
    "引擎Unity3D/3 URP精粹/架构",
    "技术美术/7 PBR/PBR白皮书/bonus/[PBR-White-Paper] PBR-Material-F0-Quick-Reference-Chart.pdf",
    "引擎Unity3D/3 URP精粹/后处理",
    "技术美术/7 PBR/从0开始PBR",
    "技术美术/6 NPR/原神",
    "test",
    "技术美术/2 空间技法",
    "引擎Unity3D/1 Unity精粹/UI系统",
    "引擎Unity3D/2 Shader精粹/ShaderLab",
    "引擎Unity3D/2 Shader精粹/《Built-in》",
    "引擎Unity3D/【Unity精粹】/未命名.canvas",
    "未命名.canvas",
    "图形学/2 图形API/DX12/龙书/DX12脑图.canvas",
    "引擎Unity3D/游戏Demo/坦克大战/未命名.canvas",
    "图形学/DX12/龙书/DX12初始化.canvas",
    "testt.canvas",
    "Tools/Excalidraw/未命名.canvas",
    "Software/未命名.canvas",
    "Tools/系统安全/未命名.canvas",
    "虚幻UE/4 特效/月神3/未命名.canvas"
  ]
}